nonempty/__init__.py
nonempty/py.typed
nonempty-0.1.0.dist-info/METADATA
nonempty-0.1.0.dist-info/WHEEL
nonempty-0.1.0.dist-info/top_level.txt
nonempty-0.1.0.dist-info/RECORD
