Metadata-Version: 2.4
Name: nonempty
Version: 0.1.0
Summary: non-empty lists for Python
Author-email: Tom Bärwinkel <dev@baerwinkel.org>
License: MIT License
Requires-Python: >=3.11
